Metadata-Version: 2.1
Name: InstaAli
Version: 0.11
Summary: operation & greeting library
Home-page: UNKNOWN
Author-email: dasturchiyigit2002@gmail.com
License: UNKNOWN
Platform: UNKNOWN
